pinyinflix.py
pinyinflix-1.1.0.dist-info/DESCRIPTION.rst
pinyinflix-1.1.0.dist-info/METADATA
pinyinflix-1.1.0.dist-info/RECORD
pinyinflix-1.1.0.dist-info/WHEEL
pinyinflix-1.1.0.dist-info/entry_points.txt
pinyinflix-1.1.0.dist-info/metadata.json
pinyinflix-1.1.0.dist-info/top_level.txt
